tramway/__init__.py
tramway/__main__.py
tramway/analyzer/__init__.py
tramway/analyzer/artefact/__init__.py
tramway/analyzer/attribute/__init__.py
tramway/analyzer/attribute/abc.py
tramway/analyzer/browser/__init__.py
tramway/analyzer/env/__init__.py
tramway/analyzer/env/abc.py
tramway/analyzer/env/containers.py
tramway/analyzer/env/environments.py
tramway/analyzer/env/ssh.py
tramway/analyzer/images/__init__.py
tramway/analyzer/images/abc.py
tramway/analyzer/images/allsymbols.py
tramway/analyzer/images/draw.py
tramway/analyzer/images/mpl.py
tramway/analyzer/localizer/__init__.py
tramway/analyzer/localizer/abc.py
tramway/analyzer/mapper/__init__.py
tramway/analyzer/mapper/abc.py
tramway/analyzer/mapper/allsymbols.py
tramway/analyzer/mapper/models.py
tramway/analyzer/mapper/mpl.py
tramway/analyzer/mapper/plotly.py
tramway/analyzer/mapper/plugin.py
tramway/analyzer/mapper/utils.py
tramway/analyzer/pipeline/__init__.py
tramway/analyzer/pipeline/stages.py
tramway/analyzer/roi/__init__.py
tramway/analyzer/roi/abc.py
tramway/analyzer/roi/allsymbols.py
tramway/analyzer/roi/collections.py
tramway/analyzer/roi/mpl.py
tramway/analyzer/roi/utils.py
tramway/analyzer/sampler/__init__.py
tramway/analyzer/sampler/abc.py
tramway/analyzer/sampler/allsymbols.py
tramway/analyzer/spt_data/__init__.py
tramway/analyzer/spt_data/abc.py
tramway/analyzer/spt_data/allsymbols.py
tramway/analyzer/spt_data/mpl.py
tramway/analyzer/tesseller/__init__.py
tramway/analyzer/tesseller/abc.py
tramway/analyzer/tesseller/allsymbols.py
tramway/analyzer/tesseller/mpl.py
tramway/analyzer/tesseller/plugin.py
tramway/analyzer/tesseller/proxied.py
tramway/analyzer/tesseller/proxy.py
tramway/analyzer/tesseller/post/__init__.py
tramway/analyzer/tesseller/post/merger.py
tramway/analyzer/time/__init__.py
tramway/analyzer/time/abc.py
tramway/analyzer/time/allsymbols.py
tramway/analyzer/tracker/__init__.py
tramway/analyzer/tracker/abc.py
tramway/analyzer/tracker/allsymbols.py
tramway/core/__init__.py
tramway-0.6.9.dist-info/LICENSE
tramway-0.6.9.dist-info/METADATA
tramway-0.6.9.dist-info/WHEEL
tramway-0.6.9.dist-info/top_level.txt
tramway-0.6.9.dist-info/RECORD
