Metadata-Version: 2.2
Name: tramway
Version: 0.6.9
Summary: TRamWAy
Home-page: https://github.com/DecBayComp/TRamWAy
Author: Institut Pasteur
Author-email: francois.laurent@pasteur.fr
License: CECILL-2.1
Classifier: Intended Audience :: Science/Research
Classifier: Programming Language :: Python :: 3
Classifier: Programming Language :: Python :: 3.8
Classifier: Programming Language :: Python :: 3.9
Classifier: Programming Language :: Python :: 3.10
Classifier: Programming Language :: Python :: 3.11
Classifier: Programming Language :: Python :: 3.12
Classifier: Programming Language :: Python :: 3.13
License-File: LICENSE
Requires-Dist: six
Requires-Dist: numpy
Requires-Dist: scipy
Requires-Dist: pandas
Requires-Dist: matplotlib
Requires-Dist: rwa-python>=0.8
Requires-Dist: setuptools
Provides-Extra: animate
Requires-Dist: opencv-python; extra == "animate"
Requires-Dist: scikit-image; extra == "animate"
Requires-Dist: tqdm; extra == "animate"
Provides-Extra: roi
Requires-Dist: polytope; extra == "roi"
Requires-Dist: tqdm; extra == "roi"
Provides-Extra: webui
Requires-Dist: bokeh<2.3.0,>=2.0.2; extra == "webui"
Requires-Dist: selenium; extra == "webui"
Requires-Dist: plotly; extra == "webui"
Requires-Dist: nbformat; extra == "webui"
Provides-Extra: hpc-minimal
Requires-Dist: polytope; extra == "hpc-minimal"
Requires-Dist: stopit; extra == "hpc-minimal"
Provides-Extra: hpc
Requires-Dist: polytope; extra == "hpc"
Requires-Dist: paramiko; extra == "hpc"
Requires-Dist: stopit; extra == "hpc"
Requires-Dist: nbconvert; extra == "hpc"
Provides-Extra: full
Requires-Dist: polytope; extra == "full"
Requires-Dist: paramiko; extra == "full"
Requires-Dist: stopit; extra == "full"
Requires-Dist: nbconvert; extra == "full"
Requires-Dist: bokeh<2.3.0,>=2.0.2; extra == "full"
Requires-Dist: selenium; extra == "full"
Requires-Dist: plotly; extra == "full"
Requires-Dist: nbformat; extra == "full"
Requires-Dist: opencv-python; extra == "full"
Requires-Dist: scikit-image; extra == "full"
Requires-Dist: tqdm; extra == "full"
Dynamic: author
Dynamic: author-email
Dynamic: classifier
Dynamic: description
Dynamic: home-page
Dynamic: keywords
Dynamic: license
Dynamic: provides-extra
Dynamic: requires-dist
Dynamic: summary
